rectiou/__init__.py
rectiou/rectiou.py
rectiou-0.0.1.dist-info/METADATA
rectiou-0.0.1.dist-info/WHEEL
rectiou-0.0.1.dist-info/licenses/LICENSE
rectiou-0.0.1.dist-info/RECORD
