Metadata-Version: 2.1
Name: rectiou
Version: 0.0.1
Summary: rectiou: vectorized 2d rectangle intersection with pytorch
Author-email: Luca Bonfiglioli <luca.bonfiglioli@gmail.com>
License-Expression: Unlicense
License-File: LICENSE
Keywords: bounding box,efficient,fast,intersection,pytorch,rectangles,vectorized
Classifier: Development Status :: 4 - Beta
Classifier: Intended Audience :: Developers
Classifier: Intended Audience :: Science/Research
Classifier: License :: OSI Approved :: The Unlicense (Unlicense)
Classifier: Natural Language :: English
Classifier: Operating System :: OS Independent
Classifier: Programming Language :: Python :: 3
Classifier: Programming Language :: Python :: 3.8
Classifier: Programming Language :: Python :: 3.9
Classifier: Programming Language :: Python :: 3.10
Classifier: Topic :: Scientific/Engineering
Classifier: Topic :: Software Development
Requires-Python: >=3.8
Requires-Dist: torch
Provides-Extra: build
Requires-Dist: build; extra == 'build'
Requires-Dist: hatch; extra == 'build'
Provides-Extra: dev
Requires-Dist: black; extra == 'dev'
Requires-Dist: flake8; extra == 'dev'
Provides-Extra: tests
Requires-Dist: numpy; extra == 'tests'
Requires-Dist: opencv-python; extra == 'tests'
Requires-Dist: pytest; extra == 'tests'
Requires-Dist: pytest-cov; extra == 'tests'
